unf.py
unf-0.11.0.dist-info/COPYING
unf-0.11.0.dist-info/METADATA
unf-0.11.0.dist-info/WHEEL
unf-0.11.0.dist-info/top_level.txt
unf-0.11.0.dist-info/RECORD
