Metadata-Version: 2.1
Name: unf
Version: 0.11.0
Summary: Universal Numeric Fingerprints
Home-page: https://github.com/chaselgrove/python-unf
Author: Christian Haselgrove
Author-email: christian.haselgrove@umassmed.edu
Classifier: Development Status :: 4 - Beta
Classifier: Environment :: Console
Classifier: Intended Audience :: Science/Research
Classifier: License :: OSI Approved :: BSD License
Classifier: Operating System :: OS Independent
Classifier: Programming Language :: Python :: 3
Classifier: Topic :: Scientific/Engineering
Requires-Python: >=3.9
License-File: COPYING
